shr_parser-0.1.9.dist-info/METADATA
shr_parser-0.1.9.dist-info/WHEEL
shr_parser-0.1.9.dist-info/licenses/LICENSE
shr_parser/__init__.py
shr_parser/shr_parser.cpython-38-s390x-linux-gnu.so
shr_parser-0.1.9.dist-info/RECORD
