Metadata-Version: 2.4
Name: shr_parser
Version: 0.1.9
Classifier: Programming Language :: Rust
Classifier: Programming Language :: Python :: Implementation :: CPython
Classifier: Programming Language :: Python :: Implementation :: PyPy
License-File: LICENSE
Summary: Parses sweeps from a Signal Hound Spike file.
Author: Lasse Nielsen
Author-email: Lasse Nielsen <lasse@xerrion.dk>
License: GPL-3.0-only
Requires-Python: >=3.8, <4
Project-URL: Source Code, https://github.com/Xerrion/shr_parser_py
